{
  "day": 15,
  "title": "Building a Proper Terminal Logging Pipeline",
  "date": "2026-02-06",
  "url": "https://juribuora.github.io/blog/2026/02/06/day-15.html",
  "category": "blog",
  "tags": [],
  "slug": "day-15",
  "sourcePath": "Blog/_posts/2026-02-06-day-15.md",
  "content": "## 🎯 Goal\n\nCreate a **reliable, professional-grade terminal logging system** that:\n\n- Records _everything_ I do during a lab\n    \n- Preserves raw data for forensic accuracy\n    \n- Produces a clean, readable Markdown log suitable for Obsidian and GitHub Pages\n    \n- Requires **zero manual editing** after the session ends\n    \n\nThis is about moving from \"messy learning\" to **reproducible, auditable lab work**.\n\n---\n\n## 🧠 What I Built\n\nBy the end of the day, I designed and debugged a **two-layer logging pipeline**:\n\n### 1️⃣ Raw Log (Source of Truth)\n\n- Captured using `script`\n    \n- Stored as `session.raw.log`\n    \n- Contains:\n    \n    - Full terminal output\n        \n    - ANSI escape codes\n        \n    - Redraw artifacts\n        \n    - Prompts, usernames, hostnames\n        \n\nThis file is **never edited**. It is the equivalent of a pcap: immutable evidence.\n\n### 2️⃣ Clean Log (Human-Readable)\n\nAutomatically generated as `session.clean.md`, with:\n\n- Commands rendered in **bold**\n    \n- Command output rendered in _italic_\n    \n- No ANSI junk\n    \n- No usernames or hostnames\n    \n- Chronological, faithful reconstruction of the session\n    \n\nThis file is what I actually read, study, and publish.\n\n---\n\n## 🛠️ Core Features Implemented\n\n- `startlog <lab_name>`\n    \n    - Creates a timestamped lab folder\n        \n    - Starts a subshell that is fully recorded\n        \n- `stoplog`\n    \n    - Ends the recording cleanly\n        \n    - Automatically runs the cleaner\n        \n    - Produces the final Markdown file\n        \n- Automatic handling of:\n    \n    - ANSI escape sequences (CSI, OSC)\n        \n    - Backspaces and redraws\n        \n    - Carriage returns\n        \n\nNo manual cleanup. No copy/paste. No rewriting history.\n\n---\n\n## 🔥 Key Breakthroughs\n\n- Fixed **greedy regex** that was silently eating command output\n    \n- Learned how terminal control sequences actually behave\n    \n- Understood why raw logs must stay raw\n    \n- Built a pipeline that mirrors real-world SOC / red-team workflows\n    \n\nThis wasn’t about Bash syntax — it was about **thinking like an analyst**.\n\n---\n\n## 📌 Final Structure\n\n```\nlab_logs/\n└── 2026-02-06_201944_fix_test/\n    ├── session.raw.log    # full, untouched transcript\n    └── session.clean.md  # blog-ready Markdown\n```\n\n---\n\n## ✅ Outcome\n\nI now have a **repeatable, professional lab logging system** that:\n\n- Scales with complexity\n    \n- Preserves evidence\n    \n- Produces publishable material automatically\n    \n\nThis is a foundational tool I’ll reuse for every future Linux, privilege escalation, and red-team lab.\n\nDay 15 was about **building the tooling**, not just learning commands — and that’s a major shift.\n\n---\n\n🧠 _Next step: use this pipeline for real SUID / permission labs without touching it again._\n"
}
